{
  "id": "00000000-0000-0000-0000-000000000000",
  "prevId": "",
  "version": "7",
  "dialect": "postgresql",
  "tables": {
    "public.BOOKS": {
      "name": "BOOKS",
      "schema": "",
      "columns": {
        "id": {
          "name": "id",
          "type": "serial",
          "primaryKey": true,
          "notNull": true
        },
        "title": {
          "name": "title",
          "type": "varchar(128)",
          "primaryKey": false,
          "notNull": true
        },
        "author": {
          "name": "author",
          "type": "varchar(128)",
          "primaryKey": false,
          "notNull": true
        },
        "content": {
          "name": "content",
          "type": "text",
          "primaryKey": false,
          "notNull": false
        },
        "category": {
          "name": "category",
          "type": "varchar(128)",
          "primaryKey": false,
          "notNull": true
        },
        "publish_date": {
          "name": "publish_date",
          "type": "date",
          "primaryKey": false,
          "notNull": true
        }
      },
      "indexes": {},
      "foreignKeys": {},
      "compositePrimaryKeys": {},
      "uniqueConstraints": {},
      "checkConstraints": {},
      "policies": {},
      "isRLSEnabled": false
    },
    "public.BORROW": {
      "name": "BORROW",
      "schema": "",
      "columns": {
        "user_id": {
          "name": "user_id",
          "type": "serial",
          "primaryKey": false,
          "notNull": true
        },
        "book_id": {
          "name": "book_id",
          "type": "serial",
          "primaryKey": false,
          "notNull": true
        },
        "borrow_date": {
          "name": "borrow_date",
          "type": "date",
          "primaryKey": false,
          "notNull": true
        }
      },
      "indexes": {},
      "foreignKeys": {},
      "compositePrimaryKeys": {},
      "uniqueConstraints": {},
      "checkConstraints": {},
      "policies": {},
      "isRLSEnabled": false
    },
    "public.USERS": {
      "name": "USERS",
      "schema": "",
      "columns": {
        "id": {
          "name": "id",
          "type": "serial",
          "primaryKey": true,
          "notNull": true
        },
        "name": {
          "name": "name",
          "type": "varchar(128)",
          "primaryKey": false,
          "notNull": true
        },
        "email": {
          "name": "email",
          "type": "varchar(128)",
          "primaryKey": false,
          "notNull": true
        },
        "password": {
          "name": "password",
          "type": "varchar(512)",
          "primaryKey": false,
          "notNull": true
        },
        "trang_thai": {
          "name": "trang_thai",
          "type": "varchar",
          "primaryKey": false,
          "notNull": true,
          "default": "'active'"
        },
        "created_at": {
          "name": "created_at",
          "type": "timestamp",
          "primaryKey": false,
          "notNull": true,
          "default": "LOCALTIMESTAMP"
        },
        "updated_at": {
          "name": "updated_at",
          "type": "timestamp",
          "primaryKey": false,
          "notNull": true,
          "default": "LOCALTIMESTAMP"
        }
      },
      "indexes": {},
      "foreignKeys": {},
      "compositePrimaryKeys": {},
      "uniqueConstraints": {},
      "checkConstraints": {},
      "policies": {},
      "isRLSEnabled": false
    },
    "public.tenants": {
      "name": "tenants",
      "schema": "",
      "columns": {
        "id": {
          "name": "id",
          "type": "uuid",
          "primaryKey": false,
          "notNull": true,
          "default": "public.uuid_generate_v7()"
        },
        "name": {
          "name": "name",
          "type": "text",
          "primaryKey": false,
          "notNull": false
        },
        "created": {
          "name": "created",
          "type": "timestamp",
          "primaryKey": false,
          "notNull": true,
          "default": "LOCALTIMESTAMP"
        },
        "updated": {
          "name": "updated",
          "type": "timestamp",
          "primaryKey": false,
          "notNull": true,
          "default": "LOCALTIMESTAMP"
        },
        "deleted": {
          "name": "deleted",
          "type": "timestamp",
          "primaryKey": false,
          "notNull": false
        },
        "compute_id": {
          "name": "compute_id",
          "type": "uuid",
          "primaryKey": false,
          "notNull": false
        }
      },
      "indexes": {
        "tenants_pkey": {
          "name": "tenants_pkey",
          "columns": [
            {
              "expression": "id",
              "asc": true,
              "nulls": "last",
              "opclass": "uuid_ops",
              "isExpression": false
            }
          ],
          "isUnique": true,
          "concurrently": false,
          "method": "btree",
          "with": {}
        }
      },
      "foreignKeys": {},
      "compositePrimaryKeys": {},
      "uniqueConstraints": {},
      "checkConstraints": {},
      "policies": {},
      "isRLSEnabled": false
    }
  },
  "enums": {},
  "schemas": {},
  "sequences": {},
  "roles": {},
  "policies": {},
  "views": {},
  "_meta": {
    "schemas": {},
    "tables": {},
    "columns": {}
  },
  "internal": {
    "tables": {}
  }
}